CHANGELOG.rst
CONTRIBUTING.rst
LICENSE
README.md
pyproject.toml
chalky/__init__.py
chalky/chain.py
chalky/chalk.py
chalky/color.py
chalky/constants.py
chalky/helpers.py
chalky/interface/__init__.py
chalky/interface/ansi.py
chalky/interface/base.py
chalky/shortcuts/__init__.py
chalky/shortcuts/bg.py
chalky/shortcuts/fg.py
chalky/shortcuts/sty.py
chalky/style.py
chalky-1.0.0.dist-info/LICENSE
chalky-1.0.0.dist-info/WHEEL
chalky-1.0.0.dist-info/METADATA
chalky-1.0.0.dist-info/RECORD
