Metadata-Version: 2.1
Name: chalky
Version: 1.0.0
Summary: Simple ANSI terminal text coloring
Home-page: https://github.com/stephen-bunn/chalky
License: ISC
Keywords: chalk,terminal,color,ansi
Author: Stephen Bunn
Author-email: stephen@bunn.io
Requires-Python: >=3.8,<4.0
Classifier: Development Status :: 5 - Production/Stable
Classifier: Intended Audience :: Developers
Classifier: License :: OSI Approved
Classifier: License :: OSI Approved :: ISC License (ISCL)
Classifier: Natural Language :: English
Classifier: Operating System :: MacOS :: MacOS X
Classifier: Operating System :: Microsoft :: Windows
Classifier: Operating System :: POSIX
Classifier: Programming Language :: Python :: 3
Classifier: Programming Language :: Python :: 3.8
Classifier: Programming Language :: Python :: 3.9
Classifier: Topic :: Software Development :: Libraries :: Python Modules
Classifier: Topic :: Utilities
Provides-Extra: profile
Project-URL: Bug Tracker, https://github.com/stephen-bunn/chalky/issues
Project-URL: Documentation, https://chalky.readthedocs.io
Project-URL: Repository, https://github.com/stephen-bunn/chalky
